ppapzip.py
ppapzip-1.0.1.dist-info/entry_points.txt
ppapzip-1.0.1.dist-info/LICENSE
ppapzip-1.0.1.dist-info/WHEEL
ppapzip-1.0.1.dist-info/METADATA
ppapzip-1.0.1.dist-info/RECORD
